<?xml version="1.0" encoding="us-ascii"?>
<Catalog>
    <CUser id="MissionTransmission">
        <Instances Id="CY_Intro1">
            <Text Text="UserData/MissionTransmission/CY_Intro1_Suffix">
                <Field Id="Suffix"/>
            </Text>
            <Text Text="UserData/MissionTransmission/CY_Intro1_Name">
                <Field Id="Name"/>
            </Text>
        </Instances>
        <Instances Id="CY_Intro2">
            <Text Text="UserData/MissionTransmission/CY_Intro2_Name">
                <Field Id="Name"/>
            </Text>
            <Text Text="UserData/MissionTransmission/CY_Intro2_Suffix">
                <Field Id="Suffix"/>
            </Text>
        </Instances>
        <Instances Id="CY_Intro3">
            <Text Text="UserData/MissionTransmission/CY_Intro3_Name">
                <Field Id="Name"/>
            </Text>
            <Text Text="UserData/MissionTransmission/CY_Intro3_Suffix">
                <Field Id="Suffix"/>
            </Text>
        </Instances>
        <Instances Id="CY_Intro4">
            <Text Text="UserData/MissionTransmission/CY_Intro4_Suffix">
                <Field Id="Suffix"/>
            </Text>
            <Text Text="UserData/MissionTransmission/CY_Intro4_Name">
                <Field Id="Name"/>
            </Text>
        </Instances>
        <Instances Id="CY_SecondaryObjective">
            <Text Text="UserData/MissionTransmission/CY_SecondaryObjective_Name">
                <Field Id="Name"/>
            </Text>
            <Text Text="UserData/MissionTransmission/CY_SecondaryObjective_Suffix">
                <Field Id="Suffix"/>
            </Text>
        </Instances>
        <Instances Id="CY_SecondaryObjectiveCompleted">
            <Text Text="UserData/MissionTransmission/CY_SecondaryObjectiveCompleted_Suffix">
                <Field Id="Suffix"/>
            </Text>
            <Text Text="UserData/MissionTransmission/CY_SecondaryObjectiveCompleted_Name">
                <Field Id="Name"/>
            </Text>
        </Instances>
        <Instances Id="CY_APCReady1">
            <Text Text="UserData/MissionTransmission/CY_APCReady1_Suffix">
                <Field Id="Suffix"/>
            </Text>
        </Instances>
        <Instances Id="CY_APCReady2">
            <Text Text="UserData/MissionTransmission/CY_APCReady2_Suffix">
                <Field Id="Suffix"/>
            </Text>
        </Instances>
        <Instances Id="CY_APCReady3">
            <Text Text="UserData/MissionTransmission/CY_APCReady3_Suffix">
                <Field Id="Suffix"/>
            </Text>
        </Instances>
        <Instances Id="CY_CampCaptured1">
            <Text Text="UserData/MissionTransmission/CY_CampCaptured1_Suffix">
                <Field Id="Suffix"/>
            </Text>
        </Instances>
        <Instances Id="CY_CampCaptured2">
            <Text Text="UserData/MissionTransmission/CY_CampCaptured2_Suffix">
                <Field Id="Suffix"/>
            </Text>
        </Instances>
        <Instances Id="CY_CampCaptured3">
            <Text Text="UserData/MissionTransmission/CY_CampCaptured3_Suffix">
                <Field Id="Suffix"/>
            </Text>
        </Instances>
        <Instances Id="CY_CampIsUnderAttack1">
            <Text Text="UserData/MissionTransmission/CY_CampIsUnderAttack1_Suffix">
                <Field Id="Suffix"/>
            </Text>
        </Instances>
        <Instances Id="CY_CampIsUnderAttack2">
            <Text Text="UserData/MissionTransmission/CY_CampIsUnderAttack2_Suffix">
                <Field Id="Suffix"/>
            </Text>
        </Instances>
        <Instances Id="CY_CampIsUnderAttack3">
            <Text Text="UserData/MissionTransmission/CY_CampIsUnderAttack3_Suffix">
                <Field Id="Suffix"/>
            </Text>
        </Instances>
        <Instances Id="CY_CampIsDead1">
            <Text Text="UserData/MissionTransmission/CY_CampIsDead1_Suffix">
                <Field Id="Suffix"/>
            </Text>
        </Instances>
        <Instances Id="CY_CampIsDead2">
            <Text Text="UserData/MissionTransmission/CY_CampIsDead2_Suffix">
                <Field Id="Suffix"/>
            </Text>
        </Instances>
        <Instances Id="CY_CampIsDead3">
            <Text Text="UserData/MissionTransmission/CY_CampIsDead3_Suffix">
                <Field Id="Suffix"/>
            </Text>
        </Instances>
        <Instances Id="CY_2CampsAreDead">
            <Text Text="UserData/MissionTransmission/CY_2CampsAreDead_Suffix">
                <Field Id="Suffix"/>
            </Text>
        </Instances>
        <Instances Id="CY_2APCareDead">
            <Text Text="UserData/MissionTransmission/CY_2APCareDead_Suffix">
                <Field Id="Suffix"/>
            </Text>
        </Instances>
        <Instances Id="CY_APCIsDead1">
            <Text Text="UserData/MissionTransmission/CY_APCIsDead1_Suffix">
                <Field Id="Suffix"/>
            </Text>
        </Instances>
        <Instances Id="CY_APCIsDead2">
            <Text Text="UserData/MissionTransmission/CY_APCIsDead2_Suffix">
                <Field Id="Suffix"/>
            </Text>
        </Instances>
        <Instances Id="CY_APCIsDead3">
            <Text Text="UserData/MissionTransmission/CY_APCIsDead3_Suffix">
                <Field Id="Suffix"/>
            </Text>
        </Instances>
        <Instances Id="CY_APCIsUnderAttack1">
            <Text Text="UserData/MissionTransmission/CY_APCIsUnderAttack1_Suffix">
                <Field Id="Suffix"/>
            </Text>
        </Instances>
        <Instances Id="CY_APCIsUnderAttack2">
            <Text Text="UserData/MissionTransmission/CY_APCIsUnderAttack2_Suffix">
                <Field Id="Suffix"/>
            </Text>
        </Instances>
        <Instances Id="CY_APCIsUnderAttack3">
            <Text Text="UserData/MissionTransmission/CY_APCIsUnderAttack3_Suffix">
                <Field Id="Suffix"/>
            </Text>
        </Instances>
        <Instances Id="CY_SensorTower">
            <Text Text="UserData/MissionTransmission/CY_SensorTower_Suffix">
                <Field Id="Suffix"/>
            </Text>
        </Instances>
        <Instances Id="CY_BonusCamps">
            <Text Text="UserData/MissionTransmission/CY_BonusCamps_Suffix">
                <Field Id="Suffix"/>
            </Text>
        </Instances>
        <Instances Id="CY_Marine_CleanUpTheFacility">
            <Text Text="UserData/MissionTransmission/CY_Marine_CleanUpTheFacility_Suffix">
                <Field Id="Suffix"/>
            </Text>
        </Instances>
        <Instances Id="CY_SecondaryHoldOnFailed1">
            <Text Text="UserData/MissionTransmission/CY_SecondaryHoldOnFailed1_Suffix">
                <Field Id="Suffix"/>
            </Text>
        </Instances>
        <Instances Id="CY_SecondaryHoldOnFailed2">
            <Text Text="UserData/MissionTransmission/CY_SecondaryHoldOnFailed2_Suffix">
                <Field Id="Suffix"/>
            </Text>
        </Instances>
        <Instances Id="CY_SecondaryHoldOnFailed3">
            <Text Text="UserData/MissionTransmission/CY_SecondaryHoldOnFailed3_Suffix">
                <Field Id="Suffix"/>
            </Text>
        </Instances>
        <Instances Id="CY_SecondaryHoldOnCompleted1">
            <Text Text="UserData/MissionTransmission/CY_SecondaryHoldOnCompleted1_Suffix">
                <Field Id="Suffix"/>
            </Text>
        </Instances>
        <Instances Id="CY_SecondaryHoldOnCompleted2">
            <Text Text="UserData/MissionTransmission/CY_SecondaryHoldOnCompleted2_Suffix">
                <Field Id="Suffix"/>
            </Text>
        </Instances>
        <Instances Id="CY_SecondaryHoldOnCompleted3">
            <Text Text="UserData/MissionTransmission/CY_SecondaryHoldOnCompleted3_Suffix">
                <Field Id="Suffix"/>
            </Text>
        </Instances>
        <Instances Id="CY_LastAttack">
            <Text Text="UserData/MissionTransmission/CY_LastAttack_Suffix">
                <Field Id="Suffix"/>
            </Text>
        </Instances>
    </CUser>
</Catalog>
