<?xml version="1.0" encoding="utf-8"?>
<Catalog>
    <CUnit id="ColonistTransport">
        <LifeStart value="1500"/>
        <LifeMax value="1500"/>
        <LifeArmor value="3"/>
    </CUnit>
    <CUnit id="HybridNemesis">
        <CostResource index="Minerals" value="500"/>
    </CUnit>
    <CUnit id="ProtossDockingBayUnit">
        <Race value="Neut"/>
    </CUnit>
    <CUnit id="ProtossFrigate">
        <FogVisibility value="Hidden"/>
        <Collide index="Flying" value="0"/>
    </CUnit>
</Catalog>
