<?xml version="1.0" encoding="us-ascii"?>
<Catalog>
    <CTerrain id="DesertWorld">
        <Lighting value="CustomLight"/>
        <CliffSets value="ShakurasTempleCliff1"/>
        <FogColor value="255,107,221,87"/>
        <FogDensity value="0.170000"/>
        <FogFalloff value="0.240000"/>
        <FogStartingHeight value="0.000000"/>
    </CTerrain>
    <CTerrain id="MarSaraEx2">
        <FogColor value="255,98,49,0"/>
        <FogStartingHeight value="4.000000"/>
        <Lighting value="AiurMorning"/>
    </CTerrain>
</Catalog>
