<?xml version="1.0" encoding="utf-8"?>
<Catalog>
    <CCharacter id="ACShakurasEvacAI">
        <Gender value="Female"/>
        <Image value="Assets\Textures\purifier_guardian_portrait_static.dds"/>
        <Color value="255,84,168,0"/>
        <Variations Name="Character/Name/ACCybrosEscort/Var1" Model="PortraitShakurasGuardian">
            <DefaultCategories value="Default"/>
            <DefaultCategories value="ConversationType:Mission"/>
            <DefaultCategories value="ConversationType:Briefing"/>
            <DefaultCategories value="ConversationType:Pitch"/>
        </Variations>
    </CCharacter>
</Catalog>
